arch_analyzer/__init__.py
arch_analyzer/cli.py
arch_analyzer/agents/__init__.py
arch_analyzer/agents/abstraction-analyzer.md
arch_analyzer/agents/complexity-analyzer.md
arch_analyzer/agents/coupling-analyzer.md
arch_analyzer/agents/dependency-analyzer.md
arch_analyzer/agents/modularity-analyzer.md
arch_analyzer/agents/performance-analyzer.md
arch_analyzer/agents/security-analyzer.md
arch_analyzer/agents/standard-analyzer.md
arch_analyzer/agents/testability-analyzer.md
arch_analyzer-1.0.0.dist-info/METADATA
arch_analyzer-1.0.0.dist-info/WHEEL
arch_analyzer-1.0.0.dist-info/entry_points.txt
arch_analyzer-1.0.0.dist-info/licenses/LICENSE
arch_analyzer-1.0.0.dist-info/RECORD
