Metadata-Version: 2.4
Name: arch-analyzer
Version: 1.0.0
Summary: 基于Claude Code的源码架构设计质量分析工具，支持多维度架构缺陷检测
Project-URL: Homepage, https://github.com/username/arch-analyzer
Project-URL: Repository, https://github.com/username/arch-analyzer
Project-URL: Issues, https://github.com/username/arch-analyzer/issues
Author: Arch Analyzer Team
License: MIT License
License-File: LICENSE
Keywords: analysis,architecture,claude-code,code-quality,code-review,software-architecture,static-analysis
Classifier: Development Status :: 5 - Production/Stable
Classifier: Environment :: Console
Classifier: Intended Audience :: Developers
Classifier: License :: OSI Approved :: MIT License
Classifier: Operating System :: OS Independent
Classifier: Programming Language :: Python :: 3
Classifier: Programming Language :: Python :: 3.7
Classifier: Programming Language :: Python :: 3.8
Classifier: Programming Language :: Python :: 3.9
Classifier: Programming Language :: Python :: 3.10
Classifier: Programming Language :: Python :: 3.11
Classifier: Programming Language :: Python :: 3.12
Classifier: Topic :: Software Development :: Libraries :: Python Modules
Classifier: Topic :: Software Development :: Quality Assurance
Classifier: Topic :: Utilities
Requires-Python: >=3.7
Provides-Extra: dev
Requires-Dist: black; extra == 'dev'
Requires-Dist: flake8; extra == 'dev'
Requires-Dist: isort; extra == 'dev'
Requires-Dist: mypy; extra == 'dev'
Requires-Dist: pytest-cov; extra == 'dev'
Requires-Dist: pytest>=6.0; extra == 'dev'
